yuekseltoprak888_de_toolkit/__init__.py
yuekseltoprak888_de_toolkit/main.py
yuekseltoprak888_de_toolkit/vm.py
yuekseltoprak888_de_toolkit-0.1.0.dist-info/METADATA
yuekseltoprak888_de_toolkit-0.1.0.dist-info/WHEEL
yuekseltoprak888_de_toolkit-0.1.0.dist-info/entry_points.txt
yuekseltoprak888_de_toolkit-0.1.0.dist-info/RECORD
